setup.py
pod/__init__.py
pod/core.py
pod/db.py
pod/dict.py
pod/fn.py
pod/list.py
pod/query.py
pod/set.py
pod/typed.py
pod.egg-info/PKG-INFO
pod.egg-info/SOURCES.txt
pod.egg-info/dependency_links.txt
pod.egg-info/top_level.txt