Metadata-Version: 1.0
Name: pod
Version: 0.54.2
Summary: A Python Object Database Implemented Using cPickle and SQLite - An easy way to store and fetch Python objects
Home-page: http://code.google.com/p/pickled-object-database/
Author: Andrew Carter, et al
Author-email: andrewjcarter@gmail.com
License: MIT
Keywords: python object database pickle persistent persistence object relational mapper ODBMS ORM
Platform: UNKNOWN
